Metadata-Version: 2.1
Name: aapp-runner
Version: 0.11.0
Summary: Pytroll runner for AAPP
Home-page: https://github.com/pytroll/pytroll-aapp-runner
Author: The Pytroll Team
Author-email: pytroll@googlegroups.com
License: GPLv3
Platform: UNKNOWN
Classifier: Development Status :: 3 - Alpha
Classifier: Intended Audience :: Science/Research
Classifier: License :: OSI Approved :: GNU General Public License v3 or later (GPLv3+)
Classifier: Operating System :: OS Independent
Classifier: Programming Language :: Python
Classifier: Topic :: Scientific/Engineering
Requires-Python: >=3.7
License-File: LICENSE
